README.rst
setup.py
doodle_dashboard_display_console.egg-info/PKG-INFO
doodle_dashboard_display_console.egg-info/SOURCES.txt
doodle_dashboard_display_console.egg-info/dependency_links.txt
doodle_dashboard_display_console.egg-info/entry_points.txt
doodle_dashboard_display_console.egg-info/requires.txt
doodle_dashboard_display_console.egg-info/top_level.txt
sketchingdev/__about__.py
sketchingdev/__init__.py
sketchingdev/console.py
sketchingdev/notifications/__init__.py
sketchingdev/notifications/centre.py
sketchingdev/notifications/error.py
sketchingdev/notifications/image.py
sketchingdev/notifications/text.py
tests/sketchingdev/__init__.py
tests/sketchingdev/test_console.py
tests/sketchingdev/test_image_notification.py
tests/sketchingdev/test_text_notification.py
tests/sketchingdev/terminal/__init__.py
tests/sketchingdev/terminal/ascii_terminal.py
tests/sketchingdev/terminal/test_ascii_terminal.py